{
  "estado": "ok",
  "archivo_zip_usado": "estado_tiempo20260722.txt",
  "archivos_zip": [
    "estado_tiempo20260722.txt"
  ],
  "cantidad_estaciones": 121,
  "lineas_invalidas_muestra": [],
  "primeros_500_caracteres": "Azul;22-julio-2026;06:00;Cubierto;15 km;5.2;3.1; 95;Sudeste  9;1002.9 / \r\n Bahía Blanca;22-julio-2026;06:00;Cubierto con niebla;400 mts;-1.2;-3.9; 100;Norte  7;1012.9 / \r\n Benito Juárez;21-julio-2026;21:00;Cubierto;10 km;7.4;No se calcula; 91;Calma;993 / \r\n Bolívar;21-julio-2026;21:00;Cubierto con llovizna;9 km;9.8;No se calcula; 92;Calma;1007.4 / \r\n Campo de Mayo;21-julio-2026;21:00;Cubierto con llovizna;2.0 km;11.3;No se calcula; 97;Sudeste  11;1011.8 / \r\n Coronel Suarez;22-julio-2026;06:00;De",
  "actualizado_github": "2026-07-22T11:23:58.146469Z"
}