{
  "fuente": "Servicio Meteorológico Nacional",
  "producto": "top_nacional",
  "actualizado_github": "2026-07-19T04:22:00.205670Z",
  "ultima_actualizacion_smn": "2026-07-19T00:00:00-03:00",
  "estado": "ok",
  "desactualizado": false,
  "mensaje": "Datos actualizados.",
  "mas_calor": {
    "estacion": "Rivadavia",
    "fecha_hora": "2026-07-18T18:00:00-03:00",
    "estado": "Despejado",
    "visibilidad": "20 km",
    "temperatura": 34.0,
    "termica": 35.7,
    "humedad": 41,
    "viento_dir": "Norte",
    "viento_vel": 3,
    "presion": 975.0
  },
  "mas_frio": {
    "estacion": "Base Belgrano II",
    "fecha_hora": "2026-07-19T00:00:00-03:00",
    "estado": "Algo nublado",
    "visibilidad": "20 km",
    "temperatura": -32.1,
    "termica": null,
    "humedad": 37,
    "viento_dir": "Noreste",
    "viento_vel": 3,
    "presion": 944.0
  },
  "mayor_viento": {
    "estacion": "Base Esperanza",
    "fecha_hora": "2026-07-19T00:00:00-03:00",
    "estado": "Cubierto con nevada",
    "visibilidad": "100 mts",
    "temperatura": -19.1,
    "termica": -34.9,
    "humedad": 65,
    "viento_dir": "Oeste",
    "viento_vel": 57,
    "presion": 991.4
  },
  "mayor_humedad": {
    "estacion": "Bahía Blanca",
    "fecha_hora": "2026-07-19T00:00:00-03:00",
    "estado": "Cielo invisible con niebla",
    "visibilidad": "600 mts",
    "temperatura": 7.1,
    "termica": 5.8,
    "humedad": 100,
    "viento_dir": "Este",
    "viento_vel": 7,
    "presion": 999.6
  }
}