{
  "fuente": "Servicio Meteorológico Nacional",
  "producto": "top_nacional",
  "actualizado_github": "2026-07-01T20:21:37.066180Z",
  "ultima_actualizacion_smn": "2026-07-01T16:00:00-03:00",
  "estado": "ok",
  "desactualizado": false,
  "mensaje": "Datos actualizados.",
  "mas_calor": {
    "estacion": "Iguazú",
    "fecha_hora": "2026-07-01T16:00:00-03:00",
    "estado": "Parcialmente nublado",
    "visibilidad": "20 km",
    "temperatura": 26.5,
    "termica": 28.7,
    "humedad": 80,
    "viento_dir": "Noreste",
    "viento_vel": 5,
    "presion": 981.8
  },
  "mas_frio": {
    "estacion": "Base Belgrano II",
    "fecha_hora": "2026-07-01T15:00:00-03:00",
    "estado": "Parcialmente nublado",
    "visibilidad": "20 km",
    "temperatura": -13.6,
    "termica": -22.8,
    "humedad": 59,
    "viento_dir": "Sudeste",
    "viento_vel": 22,
    "presion": 941.2
  },
  "mayor_viento": {
    "estacion": "Ushuaia",
    "fecha_hora": "2026-07-01T16:00:00-03:00",
    "estado": "Nublado",
    "visibilidad": "30 km",
    "temperatura": 7.5,
    "termica": 2.3,
    "humedad": 79,
    "viento_dir": "Sudoeste",
    "viento_vel": 46,
    "presion": 1008.2
  },
  "mayor_humedad": {
    "estacion": "Base Carlini",
    "fecha_hora": "2026-07-01T15:00:00-03:00",
    "estado": "Parcialmente nublado con neblina",
    "visibilidad": "4.0 km",
    "temperatura": 0.0,
    "termica": -7.6,
    "humedad": 100,
    "viento_dir": "Oeste",
    "viento_vel": 42,
    "presion": 982.8
  }
}