{
  "fuente": "Servicio Meteorológico Nacional",
  "producto": "top_nacional",
  "actualizado_github": "2026-06-16T00:08:47.435146Z",
  "ultima_actualizacion_smn": "2026-06-15T19:00:00-03:00",
  "estado": "ok",
  "desactualizado": false,
  "mensaje": "Datos actualizados.",
  "mas_calor": {
    "estacion": "Villa María Del Río Seco",
    "fecha_hora": "2026-06-15T15:00:00-03:00",
    "estado": "Parcialmente nublado",
    "visibilidad": "10 km",
    "temperatura": 19.5,
    "termica": null,
    "humedad": 46,
    "viento_dir": "Este",
    "viento_vel": 9,
    "presion": 980.2
  },
  "mas_frio": {
    "estacion": "Base Marambio",
    "fecha_hora": "2026-06-15T19:00:00-03:00",
    "estado": "Cubierto con niebla",
    "visibilidad": "200 mts",
    "temperatura": -24.4,
    "termica": -43.7,
    "humedad": 16,
    "viento_dir": "Sur",
    "viento_vel": 72,
    "presion": 958.6
  },
  "mayor_viento": {
    "estacion": "Base Marambio",
    "fecha_hora": "2026-06-15T19:00:00-03:00",
    "estado": "Cubierto con niebla",
    "visibilidad": "200 mts",
    "temperatura": -24.4,
    "termica": -43.7,
    "humedad": 16,
    "viento_dir": "Sur",
    "viento_vel": 72,
    "presion": 958.6
  },
  "mayor_humedad": {
    "estacion": "Chilecito",
    "fecha_hora": "2026-06-15T09:00:00-03:00",
    "estado": "Cubierto con niebla",
    "visibilidad": "500 mts",
    "temperatura": 6.7,
    "termica": null,
    "humedad": 100,
    "viento_dir": "Calma",
    "viento_vel": 0,
    "presion": 916.0
  }
}